main.py
ddpixe_demo-0.1.0.dist-info/METADATA
ddpixe_demo-0.1.0.dist-info/WHEEL
ddpixe_demo-0.1.0.dist-info/top_level.txt
ddpixe_demo-0.1.0.dist-info/RECORD
