Metadata-Version: 2.4
Name: ddpixe-demo
Version: 0.1.0
Requires-Python: >=3.12
Requires-Dist: mcp[cli]>=1.6.0
